MANIFEST.in
README.rst
setup.cfg
setup.py
versioneer.py
bin/driveami_calibrate_rawfiles.py
bin/driveami_filter_rawfile_listing.py
bin/driveami_list_rawfiles.py
drive_ami.egg-info/PKG-INFO
drive_ami.egg-info/SOURCES.txt
drive_ami.egg-info/dependency_links.txt
drive_ami.egg-info/requires.txt
drive_ami.egg-info/top_level.txt
driveami/__init__.py
driveami/_version.py
driveami/environments.py
driveami/keys.py
driveami/reduce.py
driveami/scripts.py
driveami/serialization.py