Metadata-Version: 1.0
Name: drive-ami
Version: 1.0.0
Summary: An interface layer for scripting the AMI-Reduce pipeline.
Home-page: https://github.com/timstaley/drive-ami
Author: Tim Staley
Author-email: timstaley337@gmail.com
License: UNKNOWN
Platform: UNKNOWN
